{
    "id": "9823",
    "ident": "2UT4",
    "type": "heliport",
    "name": "Heber Valley Hospital Heliport",
    "latitude_deg": "40.49020004272461",
    "longitude_deg": "-111.40599822998047",
    "elevation_ft": "5681",
    "continent": "NA",
    "iso_country": "US",
    "iso_region": "US-UT",
    "municipality": "Heber City",
    "scheduled_service": "no",
    "gps_code": "2UT4",
    "iata_code": "",
    "local_code": "2UT4",
    "home_link": "",
    "wikipedia_link": "",
    "keywords": "",
    "runways": [
        {
            "id": "269937",
            "airport_ref": "9823",
            "airport_ident": "2UT4",
            "length_ft": "40",
            "width_ft": "40",
            "surface": "CONC-G",
            "lighted": "0",
            "closed": "0",
            "le_ident": "H1",
            "le_latitude_deg": "",
            "le_longitude_deg": "",
            "le_elevation_ft": "",
            "le_heading_degT": "",
            "le_displaced_threshold_ft": "",
            "he_ident": "",
            "he_latitude_deg": "",
            "he_longitude_deg": "",
            "he_elevation_ft": "",
            "he_heading_degT": "",
            "he_displaced_threshold_ft": ""
        }
    ]
}