{
    "id": "345766",
    "ident": "2UT5",
    "type": "small_airport",
    "name": "Charlevoix Airport",
    "latitude_deg": "37.447504",
    "longitude_deg": "-113.247102",
    "elevation_ft": "5300",
    "continent": "NA",
    "iso_country": "US",
    "iso_region": "US-UT",
    "municipality": "New Harmony",
    "scheduled_service": "no",
    "gps_code": "2UT5",
    "iata_code": "",
    "local_code": "2UT5",
    "home_link": "",
    "wikipedia_link": "",
    "keywords": "",
    "runways": [
        {
            "id": "345767",
            "airport_ref": "345766",
            "airport_ident": "2UT5",
            "length_ft": "400",
            "width_ft": "80",
            "surface": "Dirt",
            "lighted": "0",
            "closed": "0",
            "le_ident": "2",
            "le_latitude_deg": "",
            "le_longitude_deg": "",
            "le_elevation_ft": "",
            "le_heading_degT": "",
            "le_displaced_threshold_ft": "",
            "he_ident": "20",
            "he_latitude_deg": "",
            "he_longitude_deg": "",
            "he_elevation_ft": "",
            "he_heading_degT": "",
            "he_displaced_threshold_ft": ""
        }
    ]
}