{
    "id": "347970",
    "ident": "35TN",
    "type": "heliport",
    "name": "DeKalb Community Hospital Heliport",
    "latitude_deg": "35.960944",
    "longitude_deg": "-85.830211",
    "elevation_ft": "1114",
    "continent": "NA",
    "iso_country": "US",
    "iso_region": "US-TN",
    "municipality": "Smithville",
    "scheduled_service": "no",
    "gps_code": "35TN",
    "iata_code": "",
    "local_code": "35TN",
    "home_link": "https://healthcare.ascension.org/locations/tennessee/tnnas/smithville-ascension-saint-thomas-dekalb",
    "wikipedia_link": "",
    "keywords": "Saint Thomas DeKalb",
    "runways": [
        {
            "id": "347973",
            "airport_ref": "347970",
            "airport_ident": "35TN",
            "length_ft": "80",
            "width_ft": "80",
            "surface": "ASP",
            "lighted": "1",
            "closed": "0",
            "le_ident": "H1",
            "le_latitude_deg": "",
            "le_longitude_deg": "",
            "le_elevation_ft": "",
            "le_heading_degT": "",
            "le_displaced_threshold_ft": "",
            "he_ident": "",
            "he_latitude_deg": "",
            "he_longitude_deg": "",
            "he_elevation_ft": "",
            "he_heading_degT": "",
            "he_displaced_threshold_ft": ""
        }
    ]
}