{
    "id": "11116",
    "ident": "45GA",
    "type": "closed",
    "name": "Hyatt Regency Hotel Heliport",
    "latitude_deg": "32.081911",
    "longitude_deg": "-81.091472",
    "elevation_ft": "123",
    "continent": "NA",
    "iso_country": "US",
    "iso_region": "US-GA",
    "municipality": "Savannah",
    "scheduled_service": "no",
    "gps_code": "",
    "iata_code": "",
    "local_code": "",
    "home_link": "",
    "wikipedia_link": "",
    "keywords": "45GA",
    "runways": [
        {
            "id": "346404",
            "airport_ref": "11116",
            "airport_ident": "45GA",
            "length_ft": "20",
            "width_ft": "20",
            "surface": "ASP",
            "lighted": "0",
            "closed": "0",
            "le_ident": "H1",
            "le_latitude_deg": "",
            "le_longitude_deg": "",
            "le_elevation_ft": "",
            "le_heading_degT": "",
            "le_displaced_threshold_ft": "",
            "he_ident": "",
            "he_latitude_deg": "",
            "he_longitude_deg": "",
            "he_elevation_ft": "",
            "he_heading_degT": "",
            "he_displaced_threshold_ft": ""
        },
        {
            "id": "346405",
            "airport_ref": "11116",
            "airport_ident": "45GA",
            "length_ft": "20",
            "width_ft": "20",
            "surface": "ASP",
            "lighted": "0",
            "closed": "0",
            "le_ident": "H2",
            "le_latitude_deg": "",
            "le_longitude_deg": "",
            "le_elevation_ft": "",
            "le_heading_degT": "",
            "le_displaced_threshold_ft": "",
            "he_ident": "",
            "he_latitude_deg": "",
            "he_longitude_deg": "",
            "he_elevation_ft": "",
            "he_heading_degT": "",
            "he_displaced_threshold_ft": ""
        }
    ]
}