{
    "id": "308586",
    "ident": "AYRB",
    "type": "closed",
    "name": "Lakunai Airfield",
    "latitude_deg": "-4.223",
    "longitude_deg": "152.185",
    "elevation_ft": "30",
    "continent": "OC",
    "iso_country": "PG",
    "iso_region": "PG-EBR",
    "municipality": "Rabaul",
    "scheduled_service": "no",
    "gps_code": "",
    "iata_code": "",
    "local_code": "",
    "home_link": "",
    "wikipedia_link": "https://en.wikipedia.org/wiki/Lakunai_Airfield",
    "keywords": "RAB, Old Rabaul Airport, AYRB"
}