{
    "id": "39920",
    "ident": "CA-0274",
    "type": "closed",
    "name": "Paradise River Airport",
    "latitude_deg": "53.426772",
    "longitude_deg": "-57.23156",
    "elevation_ft": "72",
    "continent": "NA",
    "iso_country": "CA",
    "iso_region": "CA-NL",
    "municipality": "",
    "scheduled_service": "no",
    "gps_code": "",
    "iata_code": "",
    "local_code": "",
    "home_link": "",
    "wikipedia_link": "https://en.wikipedia.org/wiki/Paradise_River_Airport",
    "keywords": "CDF4, YDE, YDE"
}