{
    "id": "44091",
    "ident": "CN-0015",
    "type": "medium_airport",
    "name": "Huairen Air Base",
    "latitude_deg": "39.717499",
    "longitude_deg": "113.142998",
    "elevation_ft": "3260",
    "continent": "AS",
    "iso_country": "CN",
    "iso_region": "CN-14",
    "municipality": "Shuozhou",
    "scheduled_service": "no",
    "gps_code": "",
    "iata_code": "",
    "local_code": "",
    "home_link": "",
    "wikipedia_link": "https://en.wikipedia.org/wiki/Huairen_Air_Base",
    "keywords": "Datong Huairen Airport"
}