{
    "id": "2192",
    "ident": "EDAV",
    "type": "small_airport",
    "name": "Flugplatz Eberswalde-Finow",
    "latitude_deg": "52.827221",
    "longitude_deg": "13.693611",
    "elevation_ft": "121",
    "continent": "EU",
    "iso_country": "DE",
    "iso_region": "DE-BR",
    "municipality": "Eberswalde",
    "scheduled_service": "no",
    "gps_code": "EDAV",
    "iata_code": "",
    "local_code": "",
    "home_link": "",
    "wikipedia_link": "",
    "keywords": "",
    "runways": [
        {
            "id": "236204",
            "airport_ref": "2192",
            "airport_ident": "EDAV",
            "length_ft": "8268",
            "width_ft": "164",
            "surface": "CON",
            "lighted": "1",
            "closed": "0",
            "le_ident": "10",
            "le_latitude_deg": "52.8291015625",
            "le_longitude_deg": "13.675100326538086",
            "le_elevation_ft": "112",
            "le_heading_degT": "99.9",
            "le_displaced_threshold_ft": "",
            "he_ident": "28",
            "he_latitude_deg": "52.825199127197266",
            "he_longitude_deg": "13.711899757385254",
            "he_elevation_ft": "121",
            "he_heading_degT": "279.9",
            "he_displaced_threshold_ft": ""
        }
    ]
}