{
    "id": "18385",
    "ident": "K0R0",
    "type": "small_airport",
    "name": "Columbia-Marion County Airport",
    "latitude_deg": "31.297001",
    "longitude_deg": "-89.812798",
    "elevation_ft": "265",
    "continent": "NA",
    "iso_country": "US",
    "iso_region": "US-MS",
    "municipality": "Columbia",
    "scheduled_service": "no",
    "gps_code": "",
    "iata_code": "",
    "local_code": "0R0",
    "home_link": "http://www.marioncountyms.com/columbia-marion-county-airport",
    "wikipedia_link": "",
    "keywords": "",
    "runways": [
        {
            "id": "242167",
            "airport_ref": "18385",
            "airport_ident": "K0R0",
            "length_ft": "4460",
            "width_ft": "70",
            "surface": "ASPH-G",
            "lighted": "1",
            "closed": "0",
            "le_ident": "05",
            "le_latitude_deg": "31.293399810791016",
            "le_longitude_deg": "-89.818603515625",
            "le_elevation_ft": "243",
            "le_heading_degT": "54",
            "le_displaced_threshold_ft": "646",
            "he_ident": "23",
            "he_latitude_deg": "31.300600051879883",
            "he_longitude_deg": "-89.80709838867188",
            "he_elevation_ft": "265",
            "he_heading_degT": "234",
            "he_displaced_threshold_ft": ""
        },
        {
            "id": "242168",
            "airport_ref": "18385",
            "airport_ident": "K0R0",
            "length_ft": "2430",
            "width_ft": "150",
            "surface": "GRS",
            "lighted": "0",
            "closed": "1",
            "le_ident": "13",
            "le_latitude_deg": "31.298200607299805",
            "le_longitude_deg": "-89.81729888916016",
            "le_elevation_ft": "",
            "le_heading_degT": "132",
            "le_displaced_threshold_ft": "",
            "he_ident": "31",
            "he_latitude_deg": "31.293800354003906",
            "he_longitude_deg": "-89.8115005493164",
            "he_elevation_ft": "",
            "he_heading_degT": "312",
            "he_displaced_threshold_ft": ""
        }
    ]
}