{
    "id": "18556",
    "ident": "K27A",
    "type": "small_airport",
    "name": "Elbert County Airport Patz Field",
    "latitude_deg": "34.095423",
    "longitude_deg": "-82.817581",
    "elevation_ft": "603",
    "continent": "NA",
    "iso_country": "US",
    "iso_region": "US-GA",
    "municipality": "Elberton",
    "scheduled_service": "no",
    "gps_code": "KEBA",
    "iata_code": "",
    "local_code": "EBA",
    "home_link": "",
    "wikipedia_link": "",
    "keywords": "27A",
    "runways": [
        {
            "id": "243423",
            "airport_ref": "18556",
            "airport_ident": "K27A",
            "length_ft": "4000",
            "width_ft": "75",
            "surface": "ASPH-F",
            "lighted": "1",
            "closed": "0",
            "le_ident": "10",
            "le_latitude_deg": "34.09600067138672",
            "le_longitude_deg": "-82.82240295410156",
            "le_elevation_ft": "600",
            "le_heading_degT": "99",
            "le_displaced_threshold_ft": "",
            "he_ident": "28",
            "he_latitude_deg": "34.094398498535156",
            "he_longitude_deg": "-82.8093032836914",
            "he_elevation_ft": "603",
            "he_heading_degT": "279",
            "he_displaced_threshold_ft": "299"
        }
    ]
}