{
    "id": "18823",
    "ident": "K4I7",
    "type": "small_airport",
    "name": "Putnam County Airport",
    "latitude_deg": "39.630299",
    "longitude_deg": "-86.813904",
    "elevation_ft": "842",
    "continent": "NA",
    "iso_country": "US",
    "iso_region": "US-IN",
    "municipality": "Greencastle",
    "scheduled_service": "no",
    "gps_code": "KGPC",
    "iata_code": "",
    "local_code": "GPC",
    "home_link": "http://putnamcountyregionalairport.com/index.html",
    "wikipedia_link": "https://en.wikipedia.org/wiki/Putnam_County_Airport",
    "keywords": "4I7",
    "runways": [
        {
            "id": "245443",
            "airport_ref": "18823",
            "airport_ident": "K4I7",
            "length_ft": "5000",
            "width_ft": "100",
            "surface": "ASP",
            "lighted": "1",
            "closed": "0",
            "le_ident": "18",
            "le_latitude_deg": "39.64039993286133",
            "le_longitude_deg": "-86.8135986328125",
            "le_elevation_ft": "842",
            "le_heading_degT": "181.1",
            "le_displaced_threshold_ft": "",
            "he_ident": "36",
            "he_latitude_deg": "39.62670135498047",
            "he_longitude_deg": "-86.81400299072266",
            "he_elevation_ft": "810",
            "he_heading_degT": "1.1",
            "he_displaced_threshold_ft": ""
        }
    ]
}