{
    "id": "42677",
    "ident": "KE-0034",
    "type": "small_airport",
    "name": "Orly (Olooitikosh) Airport",
    "latitude_deg": "-1.581194",
    "longitude_deg": "36.812832",
    "elevation_ft": "5600",
    "continent": "AF",
    "iso_country": "KE",
    "iso_region": "KE-700",
    "municipality": "Orly (Olooitikosh)",
    "scheduled_service": "no",
    "gps_code": "HKIK",
    "iata_code": "",
    "local_code": "ORLY",
    "home_link": "",
    "wikipedia_link": "",
    "keywords": "",
    "runways": [
        {
            "id": "354287",
            "airport_ref": "42677",
            "airport_ident": "KE-0034",
            "length_ft": "",
            "width_ft": "",
            "surface": "",
            "lighted": "0",
            "closed": "0",
            "le_ident": "10",
            "le_latitude_deg": "",
            "le_longitude_deg": "",
            "le_elevation_ft": "",
            "le_heading_degT": "",
            "le_displaced_threshold_ft": "",
            "he_ident": "28",
            "he_latitude_deg": "",
            "he_longitude_deg": "",
            "he_elevation_ft": "",
            "he_heading_degT": "",
            "he_displaced_threshold_ft": ""
        }
    ]
}