{
    "id": "20101",
    "ident": "KHWD",
    "type": "small_airport",
    "name": "Hayward Executive Airport",
    "latitude_deg": "37.659198761",
    "longitude_deg": "-122.122001648",
    "elevation_ft": "52",
    "continent": "NA",
    "iso_country": "US",
    "iso_region": "US-CA",
    "municipality": "Hayward",
    "scheduled_service": "no",
    "gps_code": "KHWD",
    "iata_code": "HWD",
    "local_code": "HWD",
    "home_link": "http://www.hayward-ca.gov/CITY-GOVERNMENT/DEPARTMENTS/PUBLIC-WORKS-ET/HEA/",
    "wikipedia_link": "https://en.wikipedia.org/wiki/Hayward_Executive_Airport",
    "keywords": "Hayward Air Terminal",
    "runways": [
        {
            "id": "245013",
            "airport_ref": "20101",
            "airport_ident": "KHWD",
            "length_ft": "3107",
            "width_ft": "75",
            "surface": "ASP",
            "lighted": "1",
            "closed": "0",
            "le_ident": "10L",
            "le_latitude_deg": "37.662498474121094",
            "le_longitude_deg": "-122.12699890136719",
            "le_elevation_ft": "28",
            "le_heading_degT": "120",
            "le_displaced_threshold_ft": "",
            "he_ident": "28R",
            "he_latitude_deg": "37.658199310302734",
            "he_longitude_deg": "-122.11799621582031",
            "he_elevation_ft": "37",
            "he_heading_degT": "300",
            "he_displaced_threshold_ft": ""
        },
        {
            "id": "245012",
            "airport_ref": "20101",
            "airport_ident": "KHWD",
            "length_ft": "5694",
            "width_ft": "150",
            "surface": "ASP",
            "lighted": "1",
            "closed": "0",
            "le_ident": "10R",
            "le_latitude_deg": "37.6619987487793",
            "le_longitude_deg": "-122.12999725341797",
            "le_elevation_ft": "29",
            "le_heading_degT": "119.8",
            "le_displaced_threshold_ft": "816",
            "he_ident": "28L",
            "he_latitude_deg": "37.654300689697266",
            "he_longitude_deg": "-122.11299896240234",
            "he_elevation_ft": "50",
            "he_heading_degT": "299.8",
            "he_displaced_threshold_ft": "676"
        }
    ]
}