{
    "id": "20851",
    "ident": "KPNM",
    "type": "small_airport",
    "name": "Princeton Municipal Airport",
    "latitude_deg": "45.55989838",
    "longitude_deg": "-93.60820007",
    "elevation_ft": "980",
    "continent": "NA",
    "iso_country": "US",
    "iso_region": "US-MN",
    "municipality": "Princeton",
    "scheduled_service": "no",
    "gps_code": "KPNM",
    "iata_code": "",
    "local_code": "PNM",
    "home_link": "",
    "wikipedia_link": "",
    "keywords": "",
    "runways": [
        {
            "id": "244602",
            "airport_ref": "20851",
            "airport_ident": "KPNM",
            "length_ft": "3900",
            "width_ft": "75",
            "surface": "ASP",
            "lighted": "1",
            "closed": "0",
            "le_ident": "15",
            "le_latitude_deg": "45.56480026245117",
            "le_longitude_deg": "-93.61109924316406",
            "le_elevation_ft": "979",
            "le_heading_degT": "158",
            "le_displaced_threshold_ft": "",
            "he_ident": "33",
            "he_latitude_deg": "45.554901123046875",
            "he_longitude_deg": "-93.60530090332031",
            "he_elevation_ft": "979",
            "he_heading_degT": "338",
            "he_displaced_threshold_ft": ""
        }
    ]
}