{
    "id": "4978",
    "ident": "NSTU",
    "type": "medium_airport",
    "name": "Pago Pago International Airport",
    "latitude_deg": "-14.331",
    "longitude_deg": "-170.710007",
    "elevation_ft": "32",
    "continent": "OC",
    "iso_country": "AS",
    "iso_region": "AS-WT",
    "municipality": "Pago Pago",
    "scheduled_service": "yes",
    "gps_code": "NSTU",
    "iata_code": "PPG",
    "local_code": "PPG",
    "home_link": "",
    "wikipedia_link": "https://en.wikipedia.org/wiki/Pago_Pago_International_Airport",
    "keywords": "",
    "runways": [
        {
            "id": "232907",
            "airport_ref": "4978",
            "airport_ident": "NSTU",
            "length_ft": "10000",
            "width_ft": "150",
            "surface": "ASP",
            "lighted": "1",
            "closed": "0",
            "le_ident": "05",
            "le_latitude_deg": "-14.340499877929688",
            "le_longitude_deg": "-170.72500610351562",
            "le_elevation_ft": "30",
            "le_heading_degT": "60.2",
            "le_displaced_threshold_ft": "1000",
            "he_ident": "23",
            "he_latitude_deg": "-14.326800346374512",
            "he_longitude_deg": "-170.7010040283203",
            "he_elevation_ft": "9",
            "he_heading_degT": "240.2",
            "he_displaced_threshold_ft": "800"
        },
        {
            "id": "232908",
            "airport_ref": "4978",
            "airport_ident": "NSTU",
            "length_ft": "3800",
            "width_ft": "100",
            "surface": "ASP",
            "lighted": "1",
            "closed": "0",
            "le_ident": "08",
            "le_latitude_deg": "-14.326899528503418",
            "le_longitude_deg": "-170.71299743652344",
            "le_elevation_ft": "6",
            "le_heading_degT": "90",
            "le_displaced_threshold_ft": "1600",
            "he_ident": "26",
            "he_latitude_deg": "-14.326899528503418",
            "he_longitude_deg": "-170.70199584960938",
            "he_elevation_ft": "5",
            "he_heading_degT": "270",
            "he_displaced_threshold_ft": ""
        }
    ]
}