{
    "id": "6089",
    "ident": "SGAY",
    "type": "medium_airport",
    "name": "Aeropuerto Nacional de Juan De Ayolas",
    "latitude_deg": "-27.378379",
    "longitude_deg": "-56.856791",
    "elevation_ft": "223",
    "continent": "SA",
    "iso_country": "PY",
    "iso_region": "PY-8",
    "municipality": "Ayolas",
    "scheduled_service": "no",
    "gps_code": "SGAY",
    "iata_code": "AYO",
    "local_code": "",
    "home_link": "",
    "wikipedia_link": "https://en.wikipedia.org/wiki/Juan_de_Ayolas_Airport",
    "keywords": "",
    "runways": [
        {
            "id": "238117",
            "airport_ref": "6089",
            "airport_ident": "SGAY",
            "length_ft": "6070",
            "width_ft": "148",
            "surface": "ASP",
            "lighted": "0",
            "closed": "0",
            "le_ident": "02",
            "le_latitude_deg": "-27.3789005279541",
            "le_longitude_deg": "-56.85559844970703",
            "le_elevation_ft": "223",
            "le_heading_degT": "10.2",
            "le_displaced_threshold_ft": "",
            "he_ident": "20",
            "he_latitude_deg": "-27.36240005493164",
            "he_longitude_deg": "-56.852298736572266",
            "he_elevation_ft": "223",
            "he_heading_degT": "190.2",
            "he_displaced_threshold_ft": ""
        }
    ]
}