{
    "id": "335941",
    "ident": "US-1533",
    "type": "small_airport",
    "name": "Locomotive Springs Airstrip",
    "latitude_deg": "41.707379",
    "longitude_deg": "-112.919873",
    "elevation_ft": "4225",
    "continent": "NA",
    "iso_country": "US",
    "iso_region": "US-UT",
    "municipality": "Snowville",
    "scheduled_service": "no",
    "gps_code": "UT94",
    "iata_code": "",
    "local_code": "UT94",
    "home_link": "https://utahbackcountrypilots.org/airstrips/LOCOMOTIVESPRINGS",
    "wikipedia_link": "",
    "keywords": ""
}