{
    "id": "26797",
    "ident": "WATE",
    "type": "small_airport",
    "name": "H. Hasan Aroeboesman (Ende) Airport",
    "latitude_deg": "-8.849114",
    "longitude_deg": "121.66101",
    "elevation_ft": "49",
    "continent": "AS",
    "iso_country": "ID",
    "iso_region": "ID-NT",
    "municipality": "Ende",
    "scheduled_service": "yes",
    "gps_code": "WATE",
    "iata_code": "ENE",
    "local_code": "",
    "home_link": "",
    "wikipedia_link": "https://en.wikipedia.org/wiki/Ende_Airport",
    "keywords": "WRKE, Isi",
    "runways": [
        {
            "id": "236489",
            "airport_ref": "26797",
            "airport_ident": "WATE",
            "length_ft": "5440",
            "width_ft": "98",
            "surface": "ASP",
            "lighted": "0",
            "closed": "0",
            "le_ident": "09",
            "le_latitude_deg": "-8.84943962097168",
            "le_longitude_deg": "121.65299987792969",
            "le_elevation_ft": "",
            "le_heading_degT": "88.9",
            "le_displaced_threshold_ft": "",
            "he_ident": "27",
            "he_latitude_deg": "-8.849149703979492",
            "he_longitude_deg": "121.66799926757812",
            "he_elevation_ft": "",
            "he_heading_degT": "268.9",
            "he_displaced_threshold_ft": ""
        }
    ]
}