{
    "id": "26813",
    "ident": "WBKD",
    "type": "medium_airport",
    "name": "Lahad Datu Airport",
    "latitude_deg": "5.032249927520752",
    "longitude_deg": "118.3239974975586",
    "elevation_ft": "45",
    "continent": "AS",
    "iso_country": "MY",
    "iso_region": "MY-12",
    "municipality": "Lahad Datu",
    "scheduled_service": "yes",
    "gps_code": "WBKD",
    "iata_code": "LDU",
    "local_code": "",
    "home_link": "",
    "wikipedia_link": "https://en.wikipedia.org/wiki/Lahad_Datu_Airport",
    "keywords": "",
    "runways": [
        {
            "id": "237817",
            "airport_ref": "26813",
            "airport_ident": "WBKD",
            "length_ft": "4498",
            "width_ft": "98",
            "surface": "ASP",
            "lighted": "1",
            "closed": "0",
            "le_ident": "11",
            "le_latitude_deg": "5.03495979309082",
            "le_longitude_deg": "118.31800079345703",
            "le_elevation_ft": "45",
            "le_heading_degT": "115.8",
            "le_displaced_threshold_ft": "",
            "he_ident": "29",
            "he_latitude_deg": "5.029540061950684",
            "he_longitude_deg": "118.33000183105469",
            "he_elevation_ft": "45",
            "he_heading_degT": "295.8",
            "he_displaced_threshold_ft": ""
        }
    ]
}