{
    "id": "9068",
    "ident": "25NC",
    "type": "small_airport",
    "name": "Smith Air Strip",
    "latitude_deg": "35.632717",
    "longitude_deg": "-79.711768",
    "elevation_ft": "560",
    "continent": "NA",
    "iso_country": "US",
    "iso_region": "US-NC",
    "municipality": "Asheboro",
    "scheduled_service": "no",
    "gps_code": "25NC",
    "iata_code": "",
    "local_code": "25NC",
    "home_link": "",
    "wikipedia_link": "",
    "keywords": "",
    "runways": [
        {
            "id": "240885",
            "airport_ref": "9068",
            "airport_ident": "25NC",
            "length_ft": "3100",
            "width_ft": "60",
            "surface": "TURF-G",
            "lighted": "1",
            "closed": "0",
            "le_ident": "18",
            "le_latitude_deg": "35.63759994506836",
            "le_longitude_deg": "-79.71070098876953",
            "le_elevation_ft": "",
            "le_heading_degT": "173",
            "le_displaced_threshold_ft": "150",
            "he_ident": "36",
            "he_latitude_deg": "35.62910079956055",
            "he_longitude_deg": "-79.70929718017578",
            "he_elevation_ft": "",
            "he_heading_degT": "",
            "he_displaced_threshold_ft": "700"
        }
    ]
}