{
    "id": "11711",
    "ident": "4TA0",
    "type": "small_airport",
    "name": "Massimiliano Memorial Field",
    "latitude_deg": "29.355499267578125",
    "longitude_deg": "-95.66380310058594",
    "elevation_ft": "65",
    "continent": "NA",
    "iso_country": "US",
    "iso_region": "US-TX",
    "municipality": "Damon",
    "scheduled_service": "no",
    "gps_code": "4TA0",
    "iata_code": "",
    "local_code": "4TA0",
    "home_link": "",
    "wikipedia_link": "",
    "keywords": "",
    "runways": [
        {
            "id": "241396",
            "airport_ref": "11711",
            "airport_ident": "4TA0",
            "length_ft": "3200",
            "width_ft": "35",
            "surface": "ASPH",
            "lighted": "1",
            "closed": "0",
            "le_ident": "17",
            "le_latitude_deg": "29.360000610351562",
            "le_longitude_deg": "-95.66470336914062",
            "le_elevation_ft": "",
            "le_heading_degT": "170",
            "le_displaced_threshold_ft": "",
            "he_ident": "35",
            "he_latitude_deg": "29.35110092163086",
            "he_longitude_deg": "-95.66310119628906",
            "he_elevation_ft": "",
            "he_heading_degT": "221",
            "he_displaced_threshold_ft": ""
        }
    ]
}