{
    "id": "15104",
    "ident": "8OA7",
    "type": "small_airport",
    "name": "Bald Eagle Field",
    "latitude_deg": "39.55649948120117",
    "longitude_deg": "-81.78099822998047",
    "elevation_ft": "680",
    "continent": "NA",
    "iso_country": "US",
    "iso_region": "US-OH",
    "municipality": "Stockport",
    "scheduled_service": "no",
    "gps_code": "8OA7",
    "iata_code": "",
    "local_code": "8OA7",
    "home_link": "",
    "wikipedia_link": "",
    "keywords": "",
    "runways": [
        {
            "id": "253179",
            "airport_ref": "15104",
            "airport_ident": "8OA7",
            "length_ft": "2260",
            "width_ft": "65",
            "surface": "TURF-G",
            "lighted": "0",
            "closed": "0",
            "le_ident": "04",
            "le_latitude_deg": "39.554500579833984",
            "le_longitude_deg": "-81.78410339355469",
            "le_elevation_ft": "680",
            "le_heading_degT": "",
            "le_displaced_threshold_ft": "",
            "he_ident": "22",
            "he_latitude_deg": "39.55849838256836",
            "he_longitude_deg": "-81.77790069580078",
            "he_elevation_ft": "680",
            "he_heading_degT": "",
            "he_displaced_threshold_ft": ""
        }
    ]
}