{
    "id": "8",
    "ident": "ANYN",
    "type": "medium_airport",
    "name": "Nauru International Airport",
    "latitude_deg": "-0.547458",
    "longitude_deg": "166.919006",
    "elevation_ft": "22",
    "continent": "OC",
    "iso_country": "NR",
    "iso_region": "NR-14",
    "municipality": "Yaren District",
    "scheduled_service": "yes",
    "gps_code": "ANYN",
    "iata_code": "INU",
    "local_code": "",
    "home_link": "",
    "wikipedia_link": "https://en.wikipedia.org/wiki/Nauru_International_Airport",
    "keywords": "ANAU",
    "runways": [
        {
            "id": "237996",
            "airport_ref": "8",
            "airport_ident": "ANYN",
            "length_ft": "7054",
            "width_ft": "148",
            "surface": "ASP",
            "lighted": "1",
            "closed": "0",
            "le_ident": "12",
            "le_latitude_deg": "-0.5411810278892517",
            "le_longitude_deg": "166.91200256347656",
            "le_elevation_ft": "22",
            "le_heading_degT": "121",
            "le_displaced_threshold_ft": "165",
            "he_ident": "30",
            "he_latitude_deg": "-0.5537390112876892",
            "he_longitude_deg": "166.92599487304688",
            "he_elevation_ft": "20",
            "he_heading_degT": "301",
            "he_displaced_threshold_ft": "380"
        }
    ]
}