{
    "id": "63",
    "ident": "AYMH",
    "type": "medium_airport",
    "name": "Mount Hagen Kagamuga Airport",
    "latitude_deg": "-5.828212",
    "longitude_deg": "144.299412",
    "elevation_ft": "5388",
    "continent": "OC",
    "iso_country": "PG",
    "iso_region": "PG-WHM",
    "municipality": "Mount Hagen",
    "scheduled_service": "yes",
    "gps_code": "AYMH",
    "iata_code": "HGU",
    "local_code": "",
    "home_link": "",
    "wikipedia_link": "https://en.wikipedia.org/wiki/Mount_Hagen_Airport",
    "keywords": "",
    "runways": [
        {
            "id": "238367",
            "airport_ref": "63",
            "airport_ident": "AYMH",
            "length_ft": "3599",
            "width_ft": "59",
            "surface": "ASP",
            "lighted": "0",
            "closed": "0",
            "le_ident": "08",
            "le_latitude_deg": "-5.827079772949219",
            "le_longitude_deg": "144.29299926757812",
            "le_elevation_ft": "5363",
            "le_heading_degT": "85",
            "le_displaced_threshold_ft": "197",
            "he_ident": "26",
            "he_latitude_deg": "-5.826149940490723",
            "he_longitude_deg": "144.30299377441406",
            "he_elevation_ft": "5363",
            "he_heading_degT": "265",
            "he_displaced_threshold_ft": "197"
        },
        {
            "id": "238368",
            "airport_ref": "63",
            "airport_ident": "AYMH",
            "length_ft": "7185",
            "width_ft": "98",
            "surface": "ASP",
            "lighted": "1",
            "closed": "0",
            "le_ident": "12",
            "le_latitude_deg": "-5.823760032653809",
            "le_longitude_deg": "144.29100036621094",
            "le_elevation_ft": "5363",
            "le_heading_degT": "121",
            "le_displaced_threshold_ft": "",
            "he_ident": "30",
            "he_latitude_deg": "-5.833980083465576",
            "he_longitude_deg": "144.30799865722656",
            "he_elevation_ft": "5363",
            "he_heading_degT": "301",
            "he_displaced_threshold_ft": ""
        }
    ]
}