{
    "id": "1689",
    "ident": "CYCG",
    "type": "medium_airport",
    "name": "Castlegar/West Kootenay Regional Airport",
    "latitude_deg": "49.2963981628",
    "longitude_deg": "-117.632003784",
    "elevation_ft": "1624",
    "continent": "NA",
    "iso_country": "CA",
    "iso_region": "CA-BC",
    "municipality": "Castlegar",
    "scheduled_service": "yes",
    "gps_code": "CYCG",
    "iata_code": "YCG",
    "local_code": "",
    "home_link": "",
    "wikipedia_link": "https://en.wikipedia.org/wiki/Castlegar_Airport",
    "keywords": "",
    "runways": [
        {
            "id": "234514",
            "airport_ref": "1689",
            "airport_ident": "CYCG",
            "length_ft": "5300",
            "width_ft": "150",
            "surface": "ASP",
            "lighted": "1",
            "closed": "0",
            "le_ident": "15",
            "le_latitude_deg": "49.30339813232422",
            "le_longitude_deg": "-117.63500213623047",
            "le_elevation_ft": "1615",
            "le_heading_degT": "169",
            "le_displaced_threshold_ft": "",
            "he_ident": "33",
            "he_latitude_deg": "49.289100646972656",
            "he_longitude_deg": "-117.62999725341797",
            "he_elevation_ft": "1621",
            "he_heading_degT": "349",
            "he_displaced_threshold_ft": ""
        }
    ]
}