{
    "id": "17128",
    "ident": "DE13",
    "type": "seaplane_base",
    "name": "Rehoboth Bay Seaplane Base",
    "latitude_deg": "38.68619918823242",
    "longitude_deg": "-75.08709716796875",
    "elevation_ft": "",
    "continent": "NA",
    "iso_country": "US",
    "iso_region": "US-DE",
    "municipality": "Dewey Beach",
    "scheduled_service": "no",
    "gps_code": "DE13",
    "iata_code": "",
    "local_code": "DE13",
    "home_link": "",
    "wikipedia_link": "",
    "keywords": ""
}