{
    "id": "2650",
    "ident": "ESGK",
    "type": "small_airport",
    "name": "Falköping Airfield",
    "latitude_deg": "58.1698",
    "longitude_deg": "13.5878",
    "elevation_ft": "785",
    "continent": "EU",
    "iso_country": "SE",
    "iso_region": "SE-Q",
    "municipality": "Falköping",
    "scheduled_service": "no",
    "gps_code": "ESGK",
    "iata_code": "",
    "local_code": "",
    "home_link": "",
    "wikipedia_link": "",
    "keywords": "",
    "runways": [
        {
            "id": "238991",
            "airport_ref": "2650",
            "airport_ident": "ESGK",
            "length_ft": "4318",
            "width_ft": "98",
            "surface": "ASP",
            "lighted": "1",
            "closed": "0",
            "le_ident": "04",
            "le_latitude_deg": "58.164798736572266",
            "le_longitude_deg": "13.581899642944336",
            "le_elevation_ft": "781",
            "le_heading_degT": "32.3",
            "le_displaced_threshold_ft": "",
            "he_ident": "22",
            "he_latitude_deg": "58.174800872802734",
            "he_longitude_deg": "13.593799591064453",
            "he_elevation_ft": "773",
            "he_heading_degT": "212.4",
            "he_displaced_threshold_ft": ""
        }
    ]
}