{
    "id": "2741",
    "ident": "ETNS",
    "type": "medium_airport",
    "name": "Schleswig Air Base",
    "latitude_deg": "54.459301",
    "longitude_deg": "9.51633",
    "elevation_ft": "70",
    "continent": "EU",
    "iso_country": "DE",
    "iso_region": "DE-SH",
    "municipality": "Jagel",
    "scheduled_service": "no",
    "gps_code": "ETNS",
    "iata_code": "WBG",
    "local_code": "",
    "home_link": "",
    "wikipedia_link": "",
    "keywords": "",
    "runways": [
        {
            "id": "236152",
            "airport_ref": "2741",
            "airport_ident": "ETNS",
            "length_ft": "8003",
            "width_ft": "98",
            "surface": "ASP",
            "lighted": "1",
            "closed": "0",
            "le_ident": "05",
            "le_latitude_deg": "54.45199966430664",
            "le_longitude_deg": "9.5024995803833",
            "le_elevation_ft": "64",
            "le_heading_degT": "47.7",
            "le_displaced_threshold_ft": "",
            "he_ident": "23",
            "he_latitude_deg": "54.46670150756836",
            "he_longitude_deg": "9.530329704284668",
            "he_elevation_ft": "65",
            "he_heading_degT": "227.7",
            "he_displaced_threshold_ft": ""
        },
        {
            "id": "236153",
            "airport_ref": "2741",
            "airport_ident": "ETNS",
            "length_ft": "6554",
            "width_ft": "148",
            "surface": "ASP",
            "lighted": "0",
            "closed": "1",
            "le_ident": "07",
            "le_latitude_deg": "54.455299377441406",
            "le_longitude_deg": "9.5024995803833",
            "le_elevation_ft": "59",
            "le_heading_degT": "74.2",
            "le_displaced_threshold_ft": "",
            "he_ident": "25",
            "he_latitude_deg": "54.46049880981445",
            "he_longitude_deg": "9.531999588012695",
            "he_elevation_ft": "70",
            "he_heading_degT": "254.2",
            "he_displaced_threshold_ft": ""
        }
    ]
}