{
    "id": "19151",
    "ident": "K8W2",
    "type": "small_airport",
    "name": "New Market Airport",
    "latitude_deg": "38.655683",
    "longitude_deg": "-78.708995",
    "elevation_ft": "975",
    "continent": "NA",
    "iso_country": "US",
    "iso_region": "US-VA",
    "municipality": "New Market",
    "scheduled_service": "no",
    "gps_code": "K8W2",
    "iata_code": "",
    "local_code": "8W2",
    "home_link": "",
    "wikipedia_link": "",
    "keywords": "Skydive Shenandoah",
    "runways": [
        {
            "id": "240383",
            "airport_ref": "19151",
            "airport_ident": "K8W2",
            "length_ft": "2920",
            "width_ft": "60",
            "surface": "ASP",
            "lighted": "1",
            "closed": "0",
            "le_ident": "06",
            "le_latitude_deg": "38.653099060058594",
            "le_longitude_deg": "-78.71199798583984",
            "le_elevation_ft": "",
            "le_heading_degT": "50.5",
            "le_displaced_threshold_ft": "",
            "he_ident": "24",
            "he_latitude_deg": "38.658199310302734",
            "he_longitude_deg": "-78.7041015625",
            "he_elevation_ft": "",
            "he_heading_degT": "230.5",
            "he_displaced_threshold_ft": "900"
        }
    ]
}