{
    "id": "21207",
    "ident": "KTNU",
    "type": "small_airport",
    "name": "Newton Municipal Airport",
    "latitude_deg": "41.6744",
    "longitude_deg": "-93.021698",
    "elevation_ft": "953",
    "continent": "NA",
    "iso_country": "US",
    "iso_region": "US-IA",
    "municipality": "Newton",
    "scheduled_service": "no",
    "gps_code": "KTNU",
    "iata_code": "TNU",
    "local_code": "TNU",
    "home_link": "http://www.newtongov.org/index.aspx?nid=189",
    "wikipedia_link": "https://en.wikipedia.org/wiki/Newton_Municipal_Airport_(Iowa)",
    "keywords": "Earl Johnson Field",
    "runways": [
        {
            "id": "242697",
            "airport_ref": "21207",
            "airport_ident": "KTNU",
            "length_ft": "5599",
            "width_ft": "100",
            "surface": "ASP",
            "lighted": "1",
            "closed": "0",
            "le_ident": "14",
            "le_latitude_deg": "41.68040084838867",
            "le_longitude_deg": "-93.0280990600586",
            "le_elevation_ft": "952",
            "le_heading_degT": "141.2",
            "le_displaced_threshold_ft": "",
            "he_ident": "32",
            "he_latitude_deg": "41.668399810791016",
            "he_longitude_deg": "-93.01529693603516",
            "he_elevation_ft": "945",
            "he_heading_degT": "321.2",
            "he_displaced_threshold_ft": ""
        }
    ]
}