{
    "id": "43286",
    "ident": "LETC",
    "type": "small_airport",
    "name": "Matilla De Los Caños Airfield",
    "latitude_deg": "41.530602",
    "longitude_deg": "-4.925",
    "elevation_ft": "2300",
    "continent": "EU",
    "iso_country": "ES",
    "iso_region": "ES-CL",
    "municipality": "Valladolid",
    "scheduled_service": "no",
    "gps_code": "LETC",
    "iata_code": "",
    "local_code": "",
    "home_link": "",
    "wikipedia_link": "",
    "keywords": "",
    "runways": [
        {
            "id": "355153",
            "airport_ref": "43286",
            "airport_ident": "LETC",
            "length_ft": "2789",
            "width_ft": "59",
            "surface": "asphalt",
            "lighted": "0",
            "closed": "0",
            "le_ident": "07",
            "le_latitude_deg": "",
            "le_longitude_deg": "",
            "le_elevation_ft": "2302",
            "le_heading_degT": "",
            "le_displaced_threshold_ft": "",
            "he_ident": "25",
            "he_latitude_deg": "",
            "he_longitude_deg": "",
            "he_elevation_ft": "2302",
            "he_heading_degT": "",
            "he_displaced_threshold_ft": ""
        }
    ]
}