{
    "id": "30004",
    "ident": "LGKY",
    "type": "small_airport",
    "name": "Kalymnos Airport",
    "latitude_deg": "36.9632987976",
    "longitude_deg": "26.9405994415",
    "elevation_ft": "771",
    "continent": "EU",
    "iso_country": "GR",
    "iso_region": "GR-L",
    "municipality": "Kalymnos Island",
    "scheduled_service": "yes",
    "gps_code": "LGKY",
    "iata_code": "JKL",
    "local_code": "",
    "home_link": "",
    "wikipedia_link": "https://en.wikipedia.org/wiki/Kalymnos_Island_National_Airport",
    "keywords": "Kalimnos, Κάλυμνος",
    "runways": [
        {
            "id": "327750",
            "airport_ref": "30004",
            "airport_ident": "LGKY",
            "length_ft": "3330",
            "width_ft": "98",
            "surface": "ASP",
            "lighted": "0",
            "closed": "0",
            "le_ident": "10",
            "le_latitude_deg": "36.964393615722656",
            "le_longitude_deg": "26.93511390686035",
            "le_elevation_ft": "750",
            "le_heading_degT": "",
            "le_displaced_threshold_ft": "",
            "he_ident": "28",
            "he_latitude_deg": "36.96251678466797",
            "he_longitude_deg": "26.946269989013672",
            "he_elevation_ft": "750",
            "he_heading_degT": "",
            "he_displaced_threshold_ft": ""
        }
    ]
}