{
    "id": "32074",
    "ident": "NZMZ",
    "type": "small_airport",
    "name": "Matakana Island Airport",
    "latitude_deg": "-37.599998474121094",
    "longitude_deg": "176.08299255371094",
    "elevation_ft": "95",
    "continent": "OC",
    "iso_country": "NZ",
    "iso_region": "NZ-BOP",
    "municipality": "Matakana Island",
    "scheduled_service": "no",
    "gps_code": "NZMZ",
    "iata_code": "",
    "local_code": "",
    "home_link": "",
    "wikipedia_link": "",
    "keywords": ""
}