{
    "id": "5178",
    "ident": "OIKR",
    "type": "medium_airport",
    "name": "Rafsanjan Airport",
    "latitude_deg": "30.298345",
    "longitude_deg": "56.048979",
    "elevation_ft": "5298",
    "continent": "AS",
    "iso_country": "IR",
    "iso_region": "IR-08",
    "municipality": "Rafsanjan",
    "scheduled_service": "yes",
    "gps_code": "OIKR",
    "iata_code": "RJN",
    "local_code": "",
    "home_link": "",
    "wikipedia_link": "https://en.wikipedia.org/wiki/Rafsanjan_Airport",
    "keywords": "",
    "runways": [
        {
            "id": "236922",
            "airport_ref": "5178",
            "airport_ident": "OIKR",
            "length_ft": "9814",
            "width_ft": "148",
            "surface": "ASP",
            "lighted": "1",
            "closed": "0",
            "le_ident": "11",
            "le_latitude_deg": "30.302799224853516",
            "le_longitude_deg": "56.03670120239258",
            "le_elevation_ft": "5258",
            "le_heading_degT": "112",
            "le_displaced_threshold_ft": "",
            "he_ident": "29",
            "he_latitude_deg": "30.292699813842773",
            "he_longitude_deg": "56.06560134887695",
            "he_elevation_ft": "5298",
            "he_heading_degT": "292",
            "he_displaced_threshold_ft": ""
        }
    ]
}