{
    "id": "5237",
    "ident": "OMFJ",
    "type": "medium_airport",
    "name": "Fujairah International Airport",
    "latitude_deg": "25.112199783325195",
    "longitude_deg": "56.32400131225586",
    "elevation_ft": "152",
    "continent": "AS",
    "iso_country": "AE",
    "iso_region": "AE-FU",
    "municipality": "",
    "scheduled_service": "yes",
    "gps_code": "OMFJ",
    "iata_code": "FJR",
    "local_code": "",
    "home_link": "",
    "wikipedia_link": "https://en.wikipedia.org/wiki/Fujairah_International_Airport",
    "keywords": "",
    "runways": [
        {
            "id": "232770",
            "airport_ref": "5237",
            "airport_ident": "OMFJ",
            "length_ft": "12303",
            "width_ft": "148",
            "surface": "ASP",
            "lighted": "1",
            "closed": "0",
            "le_ident": "11",
            "le_latitude_deg": "25.118600845336914",
            "le_longitude_deg": "56.30699920654297",
            "le_elevation_ft": "134",
            "le_heading_degT": "112.4",
            "le_displaced_threshold_ft": "2296",
            "he_ident": "29",
            "he_latitude_deg": "25.10569953918457",
            "he_longitude_deg": "56.341400146484375",
            "he_elevation_ft": "49",
            "he_heading_degT": "292.4",
            "he_displaced_threshold_ft": ""
        }
    ]
}