{
    "id": "5432",
    "ident": "PGUA",
    "type": "medium_airport",
    "name": "Andersen Air Force Base",
    "latitude_deg": "13.584",
    "longitude_deg": "144.929998",
    "elevation_ft": "627",
    "continent": "OC",
    "iso_country": "GU",
    "iso_region": "GU-U-A",
    "municipality": "Yigo",
    "scheduled_service": "no",
    "gps_code": "PGUA",
    "iata_code": "UAM",
    "local_code": "UAM",
    "home_link": "http://www.andersen.af.mil/",
    "wikipedia_link": "https://en.wikipedia.org/wiki/Andersen_Air_Force_Base",
    "keywords": "",
    "runways": [
        {
            "id": "236327",
            "airport_ref": "5432",
            "airport_ident": "PGUA",
            "length_ft": "10558",
            "width_ft": "200",
            "surface": "PEM",
            "lighted": "1",
            "closed": "0",
            "le_ident": "06L",
            "le_latitude_deg": "13.580300331115723",
            "le_longitude_deg": "144.91600036621094",
            "le_elevation_ft": "540",
            "le_heading_degT": "66",
            "le_displaced_threshold_ft": "",
            "he_ident": "24R",
            "he_latitude_deg": "13.59220027923584",
            "he_longitude_deg": "144.9429931640625",
            "he_elevation_ft": "618",
            "he_heading_degT": "246",
            "he_displaced_threshold_ft": ""
        },
        {
            "id": "236326",
            "airport_ref": "5432",
            "airport_ident": "PGUA",
            "length_ft": "11185",
            "width_ft": "200",
            "surface": "PEM",
            "lighted": "1",
            "closed": "0",
            "le_ident": "06R",
            "le_latitude_deg": "13.575300216674805",
            "le_longitude_deg": "144.91600036621094",
            "le_elevation_ft": "558",
            "le_heading_degT": "66",
            "le_displaced_threshold_ft": "",
            "he_ident": "24L",
            "he_latitude_deg": "13.587900161743164",
            "he_longitude_deg": "144.94500732421875",
            "he_elevation_ft": "608",
            "he_heading_degT": "246",
            "he_displaced_threshold_ft": ""
        }
    ]
}