{
    "id": "323564",
    "ident": "RKSU",
    "type": "heliport",
    "name": "Yeoju Range Heliport",
    "latitude_deg": "37.436895",
    "longitude_deg": "127.632886",
    "elevation_ft": "141",
    "continent": "AS",
    "iso_country": "KR",
    "iso_region": "KR-41",
    "municipality": "Utsokgogaet-gil",
    "scheduled_service": "no",
    "gps_code": "RKSU",
    "iata_code": "",
    "local_code": "",
    "home_link": "",
    "wikipedia_link": "",
    "keywords": "RKSU, Yeoju Range, Utsokgogaet"
}