{
    "id": "26544",
    "ident": "VIBL",
    "type": "small_airport",
    "name": "Bakshi Ka Talab Air Force Station",
    "latitude_deg": "26.988300323486328",
    "longitude_deg": "80.89309692382812",
    "elevation_ft": "385",
    "continent": "AS",
    "iso_country": "IN",
    "iso_region": "IN-UP",
    "municipality": "Lucknow",
    "scheduled_service": "no",
    "gps_code": "VIBL",
    "iata_code": "",
    "local_code": "",
    "home_link": "",
    "wikipedia_link": "",
    "keywords": "",
    "runways": [
        {
            "id": "236623",
            "airport_ref": "26544",
            "airport_ident": "VIBL",
            "length_ft": "8990",
            "width_ft": "150",
            "surface": "CON",
            "lighted": "1",
            "closed": "0",
            "le_ident": "09",
            "le_latitude_deg": "26.988800048828125",
            "le_longitude_deg": "80.87930297851562",
            "le_elevation_ft": "",
            "le_heading_degT": "92",
            "le_displaced_threshold_ft": "",
            "he_ident": "27",
            "he_latitude_deg": "26.987899780273438",
            "he_longitude_deg": "80.90689849853516",
            "he_elevation_ft": "",
            "he_heading_degT": "272",
            "he_displaced_threshold_ft": ""
        }
    ]
}