{
    "id": "26620",
    "ident": "VOPB",
    "type": "medium_airport",
    "name": "Veer Savarkar International Airport / INS Utkrosh",
    "latitude_deg": "11.641208",
    "longitude_deg": "92.729643",
    "elevation_ft": "13",
    "continent": "AS",
    "iso_country": "IN",
    "iso_region": "IN-AN",
    "municipality": "Port Blair",
    "scheduled_service": "yes",
    "gps_code": "VOPB",
    "iata_code": "IXZ",
    "local_code": "",
    "home_link": "",
    "wikipedia_link": "https://en.wikipedia.org/wiki/Veer_Savarkar_International_Airport",
    "keywords": "Port Blair Airport, Port Blair Air Force Station",
    "runways": [
        {
            "id": "236784",
            "airport_ref": "26620",
            "airport_ident": "VOPB",
            "length_ft": "10795",
            "width_ft": "148",
            "surface": "ASP",
            "lighted": "1",
            "closed": "0",
            "le_ident": "04",
            "le_latitude_deg": "11.629199981689453",
            "le_longitude_deg": "92.7208023071289",
            "le_elevation_ft": "11",
            "le_heading_degT": "36",
            "le_displaced_threshold_ft": "1960",
            "he_ident": "22",
            "he_latitude_deg": "11.65310001373291",
            "he_longitude_deg": "92.73870086669922",
            "he_elevation_ft": "58",
            "he_heading_degT": "216",
            "he_displaced_threshold_ft": ""
        }
    ]
}