{
    "id": "27641",
    "ident": "YINV",
    "type": "small_airport",
    "name": "Inverleigh Airport",
    "latitude_deg": "-18.005244",
    "longitude_deg": "140.535543",
    "elevation_ft": "",
    "continent": "OC",
    "iso_country": "AU",
    "iso_region": "AU-QLD",
    "municipality": "",
    "scheduled_service": "no",
    "gps_code": "YINV",
    "iata_code": "",
    "local_code": "",
    "home_link": "",
    "wikipedia_link": "",
    "keywords": "",
    "runways": [
        {
            "id": "258758",
            "airport_ref": "27641",
            "airport_ident": "YINV",
            "length_ft": "6561",
            "width_ft": "",
            "surface": "X",
            "lighted": "0",
            "closed": "0",
            "le_ident": "07",
            "le_latitude_deg": "",
            "le_longitude_deg": "",
            "le_elevation_ft": "",
            "le_heading_degT": "",
            "le_displaced_threshold_ft": "",
            "he_ident": "25",
            "he_latitude_deg": "",
            "he_longitude_deg": "",
            "he_elevation_ft": "",
            "he_heading_degT": "",
            "he_displaced_threshold_ft": ""
        },
        {
            "id": "258759",
            "airport_ref": "27641",
            "airport_ident": "YINV",
            "length_ft": "3280",
            "width_ft": "",
            "surface": "X",
            "lighted": "0",
            "closed": "0",
            "le_ident": "18",
            "le_latitude_deg": "",
            "le_longitude_deg": "",
            "le_elevation_ft": "",
            "le_heading_degT": "",
            "le_displaced_threshold_ft": "",
            "he_ident": "36",
            "he_latitude_deg": "",
            "he_longitude_deg": "",
            "he_elevation_ft": "",
            "he_heading_degT": "",
            "he_displaced_threshold_ft": ""
        }
    ]
}