{
    "id": "27951",
    "ident": "YSGT",
    "type": "small_airport",
    "name": "Singleton Airport",
    "latitude_deg": "-32.600832",
    "longitude_deg": "151.193056",
    "elevation_ft": "46",
    "continent": "OC",
    "iso_country": "AU",
    "iso_region": "AU-NSW",
    "municipality": "Singleton",
    "scheduled_service": "no",
    "gps_code": "YSGT",
    "iata_code": "SIX",
    "local_code": "",
    "home_link": "",
    "wikipedia_link": "",
    "keywords": "",
    "runways": [
        {
            "id": "259339",
            "airport_ref": "27951",
            "airport_ident": "YSGT",
            "length_ft": "3608",
            "width_ft": "",
            "surface": "B",
            "lighted": "0",
            "closed": "0",
            "le_ident": "10",
            "le_latitude_deg": "",
            "le_longitude_deg": "",
            "le_elevation_ft": "",
            "le_heading_degT": "",
            "le_displaced_threshold_ft": "",
            "he_ident": "28",
            "he_latitude_deg": "",
            "he_longitude_deg": "",
            "he_elevation_ft": "",
            "he_heading_degT": "",
            "he_displaced_threshold_ft": ""
        }
    ]
}