{
    "id": "318171",
    "ident": "ZLDL",
    "type": "small_airport",
    "name": "Delingha Airport",
    "latitude_deg": "37.125286",
    "longitude_deg": "97.268658",
    "elevation_ft": "9843",
    "continent": "AS",
    "iso_country": "CN",
    "iso_region": "CN-63",
    "municipality": "Delingha",
    "scheduled_service": "yes",
    "gps_code": "ZLDL",
    "iata_code": "HXD",
    "local_code": "",
    "home_link": "",
    "wikipedia_link": "https://en.wikipedia.org/wiki/Delingha_Airport",
    "keywords": "",
    "runways": [
        {
            "id": "354999",
            "airport_ref": "318171",
            "airport_ident": "ZLDL",
            "length_ft": "9843",
            "width_ft": "",
            "surface": "",
            "lighted": "0",
            "closed": "0",
            "le_ident": "07",
            "le_latitude_deg": "",
            "le_longitude_deg": "",
            "le_elevation_ft": "",
            "le_heading_degT": "",
            "le_displaced_threshold_ft": "",
            "he_ident": "25",
            "he_latitude_deg": "",
            "he_longitude_deg": "",
            "he_elevation_ft": "",
            "he_heading_degT": "",
            "he_displaced_threshold_ft": ""
        }
    ]
}